tenori/__init__.py
tenori/core.py
tenori/database.py
tenori/exceptions.py
tenori/hash.py
tenori-1.1.3.dist-info/LICENSE
tenori-1.1.3.dist-info/METADATA
tenori-1.1.3.dist-info/WHEEL
tenori-1.1.3.dist-info/top_level.txt
tenori-1.1.3.dist-info/RECORD
