Metadata-Version: 2.2
Name: tenori
Version: 1.1.3
Summary: A Flask package for easily adding multi-tenancy with dedicated databases
Home-page: https://github.com/TaqsBlaze/tenori
Author: Tanaka Chinengundu
Author-email: tanakah30@gmail.com
Project-URL: Bug Reports, https://github.com/TaqsBlaze/tenori/issues
Project-URL: Source, https://github.com/TaqsBlaze/tenori
Project-URL: Documentation, https://github.com/TaqsBlaze/tenori#readme
Keywords: flask,multitenant,database,sqlalchemy,tenant,saas
Classifier: Development Status :: 3 - Alpha
Classifier: Intended Audience :: Developers
Classifier: License :: OSI Approved :: MIT License
Classifier: Operating System :: OS Independent
Classifier: Programming Language :: Python :: 3
Classifier: Programming Language :: Python :: 3.7
Classifier: Programming Language :: Python :: 3.8
Classifier: Programming Language :: Python :: 3.9
Classifier: Programming Language :: Python :: 3.10
Classifier: Framework :: Flask
Classifier: Topic :: Software Development :: Libraries :: Python Modules
Classifier: Topic :: Database
Requires-Python: >=3.10
License-File: LICENSE
Requires-Dist: Flask>=2.0.0
Requires-Dist: Flask-SQLAlchemy>=2.5.0
Requires-Dist: SQLAlchemy>=1.4.0
Requires-Dist: PyMySQL>=1.0.0
Provides-Extra: dev
Requires-Dist: pytest>=6.0.0; extra == "dev"
Requires-Dist: pytest-cov>=2.0.0; extra == "dev"
Requires-Dist: black>=21.0.0; extra == "dev"
Requires-Dist: flake8>=3.9.0; extra == "dev"
Requires-Dist: mypy>=0.900; extra == "dev"
Dynamic: author
Dynamic: author-email
Dynamic: classifier
Dynamic: description
Dynamic: description-content-type
Dynamic: home-page
Dynamic: keywords
Dynamic: project-url
Dynamic: provides-extra
Dynamic: requires-dist
Dynamic: requires-python
Dynamic: summary
